{
    "total": [
        {
            "id": "100058203086218",
            "count": 5308
        },
        {
            "id": "100029891650673",
            "count": 27
        },
        {
            "id": "100007490282793",
            "count": 1874
        },
        {
            "id": "100078468122622",
            "count": 572
        },
        {
            "id": "100083942956835",
            "count": 649
        },
        {
            "id": "100041545146710",
            "count": 3520
        },
        {
            "id": "100025087129509",
            "count": 774
        },
        {
            "id": "61556763257515",
            "count": 1652
        },
        {
            "id": "100038896818576",
            "count": 1355
        },
        {
            "id": "100022818199476",
            "count": 434
        },
        {
            "id": "61559489739822",
            "count": 0
        },
        {
            "id": "100069418368781",
            "count": 1547
        },
        {
            "id": "100033166605905",
            "count": 339
        },
        {
            "id": "100003583345971",
            "count": 0
        },
        {
            "id": "100070778051069",
            "count": 49
        },
        {
            "id": "749895342",
            "count": 692
        },
        {
            "id": "100004612351549",
            "count": 19
        },
        {
            "id": "100028958234075",
            "count": 93
        },
        {
            "id": "100005300854224",
            "count": 6
        },
        {
            "id": "100091241495825",
            "count": 35
        },
        {
            "id": "100043863893529",
            "count": 4
        },
        {
            "id": "100084267287166",
            "count": 16
        },
        {
            "id": "100005329058729",
            "count": 682
        },
        {
            "id": "100073984718974",
            "count": 315
        },
        {
            "id": "61554332556294",
            "count": 3
        },
        {
            "id": "100074105132218",
            "count": 1214
        },
        {
            "id": "100087164726392",
            "count": 4680
        },
        {
            "id": "100085171900212",
            "count": 1383
        },
        {
            "id": "100063630528644",
            "count": 232
        },
        {
            "id": "100050281285568",
            "count": 65
        },
        {
            "id": "100081665837402",
            "count": 230
        },
        {
            "id": "100063877590243",
            "count": 375
        },
        {
            "id": "100091272243383",
            "count": 10
        },
        {
            "id": "100035286004549",
            "count": 834
        },
        {
            "id": "100002773121045",
            "count": 21
        },
        {
            "id": "100093002410026",
            "count": 704
        },
        {
            "id": "61551499403499",
            "count": 82
        },
        {
            "id": "100027530059979",
            "count": 2236
        },
        {
            "id": "100087504932120",
            "count": 1373
        },
        {
            "id": "100047393914858",
            "count": 123
        },
        {
            "id": "100038280105740",
            "count": 48
        },
        {
            "id": "1158392565",
            "count": 148
        },
        {
            "id": "100054300527414",
            "count": 0
        },
        {
            "id": "100009513236269",
            "count": 469
        },
        {
            "id": "100035089503648",
            "count": 592
        }
    ],
    "week": [
        {
            "id": "100058203086218",
            "count": 3,
            "name": "Nhung Mi"
        },
        {
            "id": "100029891650673",
            "count": 0,
            "name": "Trịnh Ngọc Hà"
        },
        {
            "id": "100007490282793",
            "count": 13,
            "name": "Ngô Văn Trường"
        },
        {
            "id": "100078468122622",
            "count": 0,
            "name": "Nguyễn Văn Sáng"
        },
        {
            "id": "100083942956835",
            "count": 0,
            "name": "Thanh Tuyền"
        },
        {
            "id": "100041545146710",
            "count": 0,
            "name": "Vann Anhh"
        },
        {
            "id": "100025087129509",
            "count": 0,
            "name": "Thanh Phục"
        },
        {
            "id": "61556763257515",
            "count": 20,
            "name": "Việt Hoàng"
        },
        {
            "id": "100038896818576",
            "count": 1,
            "name": "Duy Nguyễn"
        },
        {
            "id": "100022818199476",
            "count": 0,
            "name": "Bé Mon"
        },
        {
            "id": "61559489739822",
            "count": 0,
            "name": "Loan Thu"
        },
        {
            "id": "100069418368781",
            "count": 18,
            "name": "Kiều Hưng"
        },
        {
            "id": "100033166605905",
            "count": 0,
            "name": "Trần Thái Bảo"
        },
        {
            "id": "100003583345971",
            "count": 0,
            "name": "Usuário do Facebook"
        },
        {
            "id": "100070778051069",
            "count": 0,
            "name": "小香"
        },
        {
            "id": "749895342",
            "count": 0,
            "name": "Người dùng Facebook"
        },
        {
            "id": "100004612351549",
            "count": 0,
            "name": "Veronica Caccamo"
        },
        {
            "id": "100028958234075",
            "count": 0,
            "name": "Fejes Laci"
        },
        {
            "id": "100005300854224",
            "count": 0,
            "name": "Đỗ Công Thắng"
        },
        {
            "id": "100091241495825",
            "count": 0,
            "name": "Trần Minh Thư"
        },
        {
            "id": "100043863893529",
            "count": 0,
            "name": "Đức Trọng"
        },
        {
            "id": "100084267287166",
            "count": 0,
            "name": "Hoàng Long"
        },
        {
            "id": "100005329058729",
            "count": 0,
            "name": "Lê Aanh Toàn"
        },
        {
            "id": "100073984718974",
            "count": 0,
            "name": "Phạm Kiều Nhi"
        },
        {
            "id": "61554332556294",
            "count": 0,
            "name": "Ngọc Hân"
        },
        {
            "id": "100074105132218",
            "count": 0,
            "name": "Anh Dian"
        },
        {
            "id": "100087164726392",
            "count": 0,
            "name": "Nhật Lệ"
        },
        {
            "id": "100085171900212",
            "count": 7,
            "name": "Doãn Quốc Vương"
        },
        {
            "id": "100063630528644",
            "count": 0,
            "name": "Trần Văn Quang"
        },
        {
            "id": "100050281285568",
            "count": 0,
            "name": "Nguyễn Minh Mẫn"
        },
        {
            "id": "100081665837402",
            "count": 0,
            "name": "Nguyễn Thảo Vân"
        },
        {
            "id": "100063877590243",
            "count": 0,
            "name": "Văn Chiến"
        },
        {
            "id": "100091272243383",
            "count": 0,
            "name": "Trà Hiếu"
        },
        {
            "id": "100035286004549",
            "count": 0,
            "name": "Tuyền Thế Nguyễn"
        },
        {
            "id": "100002773121045",
            "count": 0,
            "name": "Đỗ Ngọc Hiếu"
        },
        {
            "id": "100093002410026",
            "count": 1,
            "name": "Cừu Trắng"
        },
        {
            "id": "61551499403499",
            "count": 0,
            "name": "Ngô Đồng"
        },
        {
            "id": "100027530059979",
            "count": 1,
            "name": "Nguyễn Đình Khôi"
        },
        {
            "id": "100087504932120",
            "count": 1,
            "name": "Hiếu Nguyễn"
        },
        {
            "id": "100047393914858",
            "count": 0,
            "name": "Phuc Bùi"
        },
        {
            "id": "100038280105740",
            "count": 0,
            "name": "Nguyễn Xuân Hiếu"
        },
        {
            "id": "1158392565",
            "count": 1,
            "name": "Miranda Wiebe"
        },
        {
            "id": "100054300527414",
            "count": 0,
            "name": "Thu Huyền"
        },
        {
            "id": "100009513236269",
            "count": 0,
            "name": "Chu Văn Việt"
        },
        {
            "id": "100035089503648",
            "count": 1,
            "name": "Cụ Văn Kính"
        }
    ],
    "day": [
        {
            "id": "100058203086218",
            "count": 3,
            "name": "Nhung Mi"
        },
        {
            "id": "100029891650673",
            "count": 0,
            "name": "Trịnh Ngọc Hà"
        },
        {
            "id": "100007490282793",
            "count": 1,
            "name": "Ngô Văn Trường"
        },
        {
            "id": "100078468122622",
            "count": 0,
            "name": "Nguyễn Văn Sáng"
        },
        {
            "id": "100083942956835",
            "count": 0,
            "name": "Thanh Tuyền"
        },
        {
            "id": "100041545146710",
            "count": 0,
            "name": "Vann Anhh"
        },
        {
            "id": "100025087129509",
            "count": 0,
            "name": "Thanh Phục"
        },
        {
            "id": "61556763257515",
            "count": 1,
            "name": "Việt Hoàng"
        },
        {
            "id": "100038896818576",
            "count": 1,
            "name": "Duy Nguyễn"
        },
        {
            "id": "100022818199476",
            "count": 0,
            "name": "Bé Mon"
        },
        {
            "id": "61559489739822",
            "count": 0,
            "name": "Loan Thu"
        },
        {
            "id": "100069418368781",
            "count": 1,
            "name": "Kiều Hưng"
        },
        {
            "id": "100033166605905",
            "count": 0,
            "name": "Trần Thái Bảo"
        },
        {
            "id": "100003583345971",
            "count": 0,
            "name": "Usuário do Facebook"
        },
        {
            "id": "100070778051069",
            "count": 0,
            "name": "小香"
        },
        {
            "id": "749895342",
            "count": 0,
            "name": "Người dùng Facebook"
        },
        {
            "id": "100004612351549",
            "count": 0,
            "name": "Veronica Caccamo"
        },
        {
            "id": "100028958234075",
            "count": 0,
            "name": "Fejes Laci"
        },
        {
            "id": "100005300854224",
            "count": 0,
            "name": "Đỗ Công Thắng"
        },
        {
            "id": "100091241495825",
            "count": 0,
            "name": "Trần Minh Thư"
        },
        {
            "id": "100043863893529",
            "count": 0,
            "name": "Đức Trọng"
        },
        {
            "id": "100084267287166",
            "count": 0,
            "name": "Hoàng Long"
        },
        {
            "id": "100005329058729",
            "count": 0,
            "name": "Lê Aanh Toàn"
        },
        {
            "id": "100073984718974",
            "count": 0,
            "name": "Phạm Kiều Nhi"
        },
        {
            "id": "61554332556294",
            "count": 0,
            "name": "Ngọc Hân"
        },
        {
            "id": "100074105132218",
            "count": 0,
            "name": "Anh Dian"
        },
        {
            "id": "100087164726392",
            "count": 0,
            "name": "Nhật Lệ"
        },
        {
            "id": "100085171900212",
            "count": 7,
            "name": "Doãn Quốc Vương"
        },
        {
            "id": "100063630528644",
            "count": 0,
            "name": "Trần Văn Quang"
        },
        {
            "id": "100050281285568",
            "count": 0,
            "name": "Nguyễn Minh Mẫn"
        },
        {
            "id": "100081665837402",
            "count": 0,
            "name": "Nguyễn Thảo Vân"
        },
        {
            "id": "100063877590243",
            "count": 0,
            "name": "Văn Chiến"
        },
        {
            "id": "100091272243383",
            "count": 0,
            "name": "Trà Hiếu"
        },
        {
            "id": "100035286004549",
            "count": 0,
            "name": "Tuyền Thế Nguyễn"
        },
        {
            "id": "100002773121045",
            "count": 0,
            "name": "Đỗ Ngọc Hiếu"
        },
        {
            "id": "100093002410026",
            "count": 0,
            "name": "Cừu Trắng"
        },
        {
            "id": "61551499403499",
            "count": 0,
            "name": "Ngô Đồng"
        },
        {
            "id": "100027530059979",
            "count": 0,
            "name": "Nguyễn Đình Khôi"
        },
        {
            "id": "100087504932120",
            "count": 0,
            "name": "Hiếu Nguyễn"
        },
        {
            "id": "100047393914858",
            "count": 0,
            "name": "Phuc Bùi"
        },
        {
            "id": "100038280105740",
            "count": 0,
            "name": "Nguyễn Xuân Hiếu"
        },
        {
            "id": "1158392565",
            "count": 1,
            "name": "Miranda Wiebe"
        },
        {
            "id": "100054300527414",
            "count": 0,
            "name": "Thu Huyền"
        },
        {
            "id": "100009513236269",
            "count": 0,
            "name": "Chu Văn Việt"
        },
        {
            "id": "100035089503648",
            "count": 0,
            "name": "Cụ Văn Kính"
        }
    ],
    "time": 2,
    "last": {
        "time": 0,
        "day": [
            {
                "id": "100058203086218",
                "count": 0
            },
            {
                "id": "100029891650673",
                "count": 0
            },
            {
                "id": "100007490282793",
                "count": 0
            },
            {
                "id": "100078468122622",
                "count": 0
            },
            {
                "id": "100020917071934",
                "count": 0
            },
            {
                "id": "100063189750540",
                "count": 0
            },
            {
                "id": "100083942956835",
                "count": 0
            },
            {
                "id": "100041545146710",
                "count": 0
            },
            {
                "id": "100087164726392",
                "count": 0
            },
            {
                "id": "100055249308416",
                "count": 0
            },
            {
                "id": "100025087129509",
                "count": 0
            },
            {
                "id": "100086469094339",
                "count": 0
            },
            {
                "id": "61556763257515",
                "count": 0
            },
            {
                "id": "100045441440428",
                "count": 0
            },
            {
                "id": "100005656444543",
                "count": 0
            },
            {
                "id": "100038896818576",
                "count": 0
            },
            {
                "id": "100022818199476",
                "count": 0
            },
            {
                "id": "100075610939839",
                "count": 0
            },
            {
                "id": "61559489739822",
                "count": 0
            },
            {
                "id": "100080818791584",
                "count": 0
            },
            {
                "id": "100069418368781",
                "count": 0
            },
            {
                "id": "100033166605905",
                "count": 0
            },
            {
                "id": "100003583345971",
                "count": 0
            },
            {
                "id": "100094161339586",
                "count": 0
            },
            {
                "id": "100044928370894",
                "count": 0
            },
            {
                "id": "100070778051069",
                "count": 0
            },
            {
                "id": "100030098591447",
                "count": 0
            },
            {
                "id": "749895342",
                "count": 0
            },
            {
                "id": "100004612351549",
                "count": 0
            },
            {
                "id": "100028958234075",
                "count": 0
            },
            {
                "id": "100081035507474",
                "count": 0
            },
            {
                "id": "100050042973543",
                "count": 0
            },
            {
                "id": "100022020611720",
                "count": 0
            },
            {
                "id": "100005300854224",
                "count": 0
            },
            {
                "id": "100002619661116",
                "count": 0
            },
            {
                "id": "100007713995242",
                "count": 0
            },
            {
                "id": "100004955410294",
                "count": 0
            },
            {
                "id": "100013319859952",
                "count": 0
            },
            {
                "id": "100052079333447",
                "count": 0
            },
            {
                "id": "100027715200123",
                "count": 0
            },
            {
                "id": "100050198361213",
                "count": 0
            },
            {
                "id": "100057210724610",
                "count": 0
            },
            {
                "id": "100077251302441",
                "count": 0
            },
            {
                "id": "100091241495825",
                "count": 0
            },
            {
                "id": "100043863893529",
                "count": 0
            },
            {
                "id": "100084267287166",
                "count": 0
            },
            {
                "id": "100005329058729",
                "count": 0
            },
            {
                "id": "100003923440108",
                "count": 0
            },
            {
                "id": "100073984718974",
                "count": 0
            },
            {
                "id": "61558839610387",
                "count": 0
            },
            {
                "id": "100005060492470",
                "count": 0
            },
            {
                "id": "100010729083169",
                "count": 0
            },
            {
                "id": "100045823793598",
                "count": 0
            },
            {
                "id": "61554332556294",
                "count": 0
            },
            {
                "id": "100074105132218",
                "count": 0
            },
            {
                "id": "100004806302875",
                "count": 0
            },
            {
                "id": "61551903212513",
                "count": 0
            },
            {
                "id": "100022676256217",
                "count": 0
            },
            {
                "id": "100056952000211",
                "count": 0
            },
            {
                "id": "100053733394127",
                "count": 0
            },
            {
                "id": "100094522523666",
                "count": 0
            },
            {
                "id": "100070185429796",
                "count": 0
            },
            {
                "id": "100053305883896",
                "count": 0
            },
            {
                "id": "100056649600478",
                "count": 0
            },
            {
                "id": "100085171900212",
                "count": 0
            },
            {
                "id": "100036817152589",
                "count": 0
            },
            {
                "id": "100035136464818",
                "count": 0
            },
            {
                "id": "100044582110894",
                "count": 0
            },
            {
                "id": "100055928420689",
                "count": 0
            },
            {
                "id": "100004045521625",
                "count": 0
            },
            {
                "id": "100063630528644",
                "count": 0
            },
            {
                "id": "100035089503648",
                "count": 0
            },
            {
                "id": "100017685783438",
                "count": 0
            },
            {
                "id": "100076068117686",
                "count": 0
            },
            {
                "id": "100050281285568",
                "count": 0
            },
            {
                "id": "100034891294084",
                "count": 0
            },
            {
                "id": "100013423815734",
                "count": 0
            },
            {
                "id": "100027530059979",
                "count": 0
            },
            {
                "id": "100019036960085",
                "count": 0
            },
            {
                "id": "100081665837402",
                "count": 0
            },
            {
                "id": "100089909431563",
                "count": 0
            },
            {
                "id": "100063877590243",
                "count": 0
            },
            {
                "id": "100069071392082",
                "count": 0
            },
            {
                "id": "100050005270159",
                "count": 0
            },
            {
                "id": "61558347998634",
                "count": 0
            },
            {
                "id": "100091272243383",
                "count": 0
            },
            {
                "id": "100035286004549",
                "count": 0
            },
            {
                "id": "100002773121045",
                "count": 0
            },
            {
                "id": "100073375130181",
                "count": 0
            },
            {
                "id": "100017371809756",
                "count": 0
            },
            {
                "id": "100093002410026",
                "count": 0
            },
            {
                "id": "100041860153361",
                "count": 0
            },
            {
                "id": "100034649301312",
                "count": 0
            },
            {
                "id": "100008638083585",
                "count": 0
            },
            {
                "id": "61551499403499",
                "count": 0
            },
            {
                "id": "100023074744797",
                "count": 0
            },
            {
                "id": "61558485640180",
                "count": 0
            },
            {
                "id": "100053629545566",
                "count": 0
            },
            {
                "id": "100066522933945",
                "count": 0
            },
            {
                "id": "61552017850928",
                "count": 0
            },
            {
                "id": "100094910581193",
                "count": 0
            },
            {
                "id": "100087504932120",
                "count": 0
            },
            {
                "id": "100047393914858",
                "count": 0
            },
            {
                "id": "100087157105680",
                "count": 0
            },
            {
                "id": "100089821665471",
                "count": 0
            },
            {
                "id": "100087756567398",
                "count": 0
            },
            {
                "id": "100038280105740",
                "count": 0
            },
            {
                "id": "100085891523026",
                "count": 0
            },
            {
                "id": "100069782653917",
                "count": 0
            },
            {
                "id": "100064188130935",
                "count": 0
            },
            {
                "id": "100058554495010",
                "count": 0
            },
            {
                "id": "100040581034062",
                "count": 0
            },
            {
                "id": "100028023143540",
                "count": 0
            },
            {
                "id": "100069171423576",
                "count": 0
            },
            {
                "id": "1158392565",
                "count": 0
            },
            {
                "id": "100072407247125",
                "count": 0
            },
            {
                "id": "100004510740941",
                "count": 0
            },
            {
                "id": "100008726685231",
                "count": 0
            },
            {
                "id": "100024203220181",
                "count": 0
            },
            {
                "id": "100054300527414",
                "count": 0
            },
            {
                "id": "100082363614790",
                "count": 0
            },
            {
                "id": "100009513236269",
                "count": 0
            },
            {
                "id": "100010632666572",
                "count": 0
            }
        ],
        "week": [
            {
                "id": "100058203086218",
                "count": 0
            },
            {
                "id": "100029891650673",
                "count": 0
            },
            {
                "id": "100007490282793",
                "count": 0
            },
            {
                "id": "100078468122622",
                "count": 0
            },
            {
                "id": "100020917071934",
                "count": 0
            },
            {
                "id": "100063189750540",
                "count": 0
            },
            {
                "id": "100083942956835",
                "count": 0
            },
            {
                "id": "100041545146710",
                "count": 0
            },
            {
                "id": "100087164726392",
                "count": 0
            },
            {
                "id": "100055249308416",
                "count": 0
            },
            {
                "id": "100025087129509",
                "count": 0
            },
            {
                "id": "100086469094339",
                "count": 0
            },
            {
                "id": "61556763257515",
                "count": 0
            },
            {
                "id": "100045441440428",
                "count": 0
            },
            {
                "id": "100005656444543",
                "count": 0
            },
            {
                "id": "100038896818576",
                "count": 0
            },
            {
                "id": "100022818199476",
                "count": 0
            },
            {
                "id": "100075610939839",
                "count": 0
            },
            {
                "id": "61559489739822",
                "count": 0
            },
            {
                "id": "100080818791584",
                "count": 0
            },
            {
                "id": "100069418368781",
                "count": 0
            },
            {
                "id": "100033166605905",
                "count": 0
            },
            {
                "id": "100003583345971",
                "count": 0
            },
            {
                "id": "100094161339586",
                "count": 0
            },
            {
                "id": "100044928370894",
                "count": 0
            },
            {
                "id": "100070778051069",
                "count": 0
            },
            {
                "id": "100030098591447",
                "count": 0
            },
            {
                "id": "749895342",
                "count": 0
            },
            {
                "id": "100004612351549",
                "count": 0
            },
            {
                "id": "100028958234075",
                "count": 0
            },
            {
                "id": "100081035507474",
                "count": 0
            },
            {
                "id": "100050042973543",
                "count": 0
            },
            {
                "id": "100022020611720",
                "count": 0
            },
            {
                "id": "100005300854224",
                "count": 0
            },
            {
                "id": "100002619661116",
                "count": 0
            },
            {
                "id": "100007713995242",
                "count": 0
            },
            {
                "id": "100004955410294",
                "count": 0
            },
            {
                "id": "100013319859952",
                "count": 0
            },
            {
                "id": "100052079333447",
                "count": 0
            },
            {
                "id": "100027715200123",
                "count": 0
            },
            {
                "id": "100050198361213",
                "count": 0
            },
            {
                "id": "100057210724610",
                "count": 0
            },
            {
                "id": "100077251302441",
                "count": 0
            },
            {
                "id": "100091241495825",
                "count": 0
            },
            {
                "id": "100043863893529",
                "count": 0
            },
            {
                "id": "100084267287166",
                "count": 0
            },
            {
                "id": "100005329058729",
                "count": 0
            },
            {
                "id": "100003923440108",
                "count": 0
            },
            {
                "id": "100073984718974",
                "count": 0
            },
            {
                "id": "61558839610387",
                "count": 0
            },
            {
                "id": "100005060492470",
                "count": 0
            },
            {
                "id": "100010729083169",
                "count": 0
            },
            {
                "id": "100045823793598",
                "count": 0
            },
            {
                "id": "61554332556294",
                "count": 0
            },
            {
                "id": "100074105132218",
                "count": 0
            },
            {
                "id": "100004806302875",
                "count": 0
            },
            {
                "id": "61551903212513",
                "count": 0
            },
            {
                "id": "100022676256217",
                "count": 0
            },
            {
                "id": "100056952000211",
                "count": 0
            },
            {
                "id": "100053733394127",
                "count": 0
            },
            {
                "id": "100094522523666",
                "count": 0
            },
            {
                "id": "100070185429796",
                "count": 0
            },
            {
                "id": "100053305883896",
                "count": 0
            },
            {
                "id": "100056649600478",
                "count": 0
            },
            {
                "id": "100085171900212",
                "count": 0
            },
            {
                "id": "100036817152589",
                "count": 0
            },
            {
                "id": "100035136464818",
                "count": 0
            },
            {
                "id": "100044582110894",
                "count": 0
            },
            {
                "id": "100055928420689",
                "count": 0
            },
            {
                "id": "100004045521625",
                "count": 0
            },
            {
                "id": "100063630528644",
                "count": 0
            },
            {
                "id": "100035089503648",
                "count": 0
            },
            {
                "id": "100017685783438",
                "count": 0
            },
            {
                "id": "100076068117686",
                "count": 0
            },
            {
                "id": "100050281285568",
                "count": 0
            },
            {
                "id": "100034891294084",
                "count": 0
            },
            {
                "id": "100013423815734",
                "count": 0
            },
            {
                "id": "100027530059979",
                "count": 0
            },
            {
                "id": "100019036960085",
                "count": 0
            },
            {
                "id": "100081665837402",
                "count": 0
            },
            {
                "id": "100089909431563",
                "count": 0
            },
            {
                "id": "100063877590243",
                "count": 0
            },
            {
                "id": "100069071392082",
                "count": 0
            },
            {
                "id": "100050005270159",
                "count": 0
            },
            {
                "id": "61558347998634",
                "count": 0
            },
            {
                "id": "100091272243383",
                "count": 0
            },
            {
                "id": "100035286004549",
                "count": 0
            },
            {
                "id": "100002773121045",
                "count": 0
            },
            {
                "id": "100073375130181",
                "count": 0
            },
            {
                "id": "100017371809756",
                "count": 0
            },
            {
                "id": "100093002410026",
                "count": 0
            },
            {
                "id": "100041860153361",
                "count": 0
            },
            {
                "id": "100034649301312",
                "count": 0
            },
            {
                "id": "100008638083585",
                "count": 0
            },
            {
                "id": "61551499403499",
                "count": 0
            },
            {
                "id": "100023074744797",
                "count": 0
            },
            {
                "id": "61558485640180",
                "count": 0
            },
            {
                "id": "100053629545566",
                "count": 0
            },
            {
                "id": "100066522933945",
                "count": 0
            },
            {
                "id": "61552017850928",
                "count": 0
            },
            {
                "id": "100094910581193",
                "count": 0
            },
            {
                "id": "100087504932120",
                "count": 0
            },
            {
                "id": "100047393914858",
                "count": 0
            },
            {
                "id": "100087157105680",
                "count": 0
            },
            {
                "id": "100089821665471",
                "count": 0
            },
            {
                "id": "100087756567398",
                "count": 0
            },
            {
                "id": "100038280105740",
                "count": 0
            },
            {
                "id": "100085891523026",
                "count": 0
            },
            {
                "id": "100069782653917",
                "count": 0
            },
            {
                "id": "100064188130935",
                "count": 0
            },
            {
                "id": "100058554495010",
                "count": 0
            },
            {
                "id": "100040581034062",
                "count": 0
            },
            {
                "id": "100028023143540",
                "count": 0
            },
            {
                "id": "100069171423576",
                "count": 0
            },
            {
                "id": "1158392565",
                "count": 0
            },
            {
                "id": "100072407247125",
                "count": 0
            },
            {
                "id": "100004510740941",
                "count": 0
            },
            {
                "id": "100008726685231",
                "count": 0
            },
            {
                "id": "100024203220181",
                "count": 0
            },
            {
                "id": "100054300527414",
                "count": 0
            },
            {
                "id": "100082363614790",
                "count": 0
            },
            {
                "id": "100009513236269",
                "count": 0
            },
            {
                "id": "100010632666572",
                "count": 0
            }
        ]
    }
}