{
    "total": [
        {
            "id": "100065516136762",
            "count": 82
        },
        {
            "id": "61553962150623",
            "count": 3132
        },
        {
            "id": "100093791194651",
            "count": 842
        },
        {
            "id": "100029891650673",
            "count": 49
        },
        {
            "id": "1158392565",
            "count": 6218
        },
        {
            "id": "100002967609950",
            "count": 74
        },
        {
            "id": "61566316212795",
            "count": 6181
        },
        {
            "id": "100090129305788",
            "count": 1112
        },
        {
            "id": "100006936944673",
            "count": 145
        },
        {
            "id": "100078387196065",
            "count": 271
        },
        {
            "id": "100026964950417",
            "count": 1365
        },
        {
            "id": "100045699785906",
            "count": 156
        },
        {
            "id": "61555471987398",
            "count": 121
        },
        {
            "id": "100080190861969",
            "count": 51
        },
        {
            "id": "100095363708552",
            "count": 146
        },
        {
            "id": "100005888041145",
            "count": 73
        },
        {
            "id": "100091429430126",
            "count": 191
        },
        {
            "id": "100034372458968",
            "count": 3512
        },
        {
            "id": "100088357192531",
            "count": 865
        },
        {
            "id": "100082047108350",
            "count": 950
        },
        {
            "id": "100061614405741",
            "count": 36
        },
        {
            "id": "100065251602724",
            "count": 518
        },
        {
            "id": "100086991830331",
            "count": 2103
        },
        {
            "id": "100072659419001",
            "count": 94
        },
        {
            "id": "100087208038222",
            "count": 512
        },
        {
            "id": "100063787487497",
            "count": 1109
        },
        {
            "id": "100087957049611",
            "count": 3587
        },
        {
            "id": "100024752473193",
            "count": 184
        },
        {
            "id": "100093026747618",
            "count": 39
        },
        {
            "id": "100083942956835",
            "count": 164
        },
        {
            "id": "61554009424917",
            "count": 56
        },
        {
            "id": "100077289021351",
            "count": 74
        },
        {
            "id": "100087926503920",
            "count": 184
        },
        {
            "id": "61554712072326",
            "count": 309
        },
        {
            "id": "100039470115552",
            "count": 319
        },
        {
            "id": "61556481320309",
            "count": 176
        },
        {
            "id": "100089269775183",
            "count": 27
        },
        {
            "id": "100020528575783",
            "count": 28
        },
        {
            "id": "100024133790484",
            "count": 30
        },
        {
            "id": "100046292103991",
            "count": 284
        },
        {
            "id": "100028370918283",
            "count": 59
        },
        {
            "id": "100072236886559",
            "count": 68
        },
        {
            "id": "1578092979",
            "count": 178
        },
        {
            "id": "100014679373226",
            "count": 12
        },
        {
            "id": "61566536774365",
            "count": 98
        },
        {
            "id": "100065563803743",
            "count": 54
        },
        {
            "id": "100020953182001",
            "count": 26
        },
        {
            "id": "100034985235308",
            "count": 244
        },
        {
            "id": "100073619405321",
            "count": 271
        },
        {
            "id": "100090989239372",
            "count": 167
        },
        {
            "id": "100088520275551",
            "count": 48
        },
        {
            "id": "100050284906760",
            "count": 37
        },
        {
            "id": "100088684481575",
            "count": 20
        },
        {
            "id": "100075683283542",
            "count": 28
        },
        {
            "id": "100088285105412",
            "count": 12
        },
        {
            "id": "100084739688576",
            "count": 5
        },
        {
            "id": "100082452546345",
            "count": 9
        },
        {
            "id": "61559416928399",
            "count": 16
        },
        {
            "id": "100095397240263",
            "count": 61
        },
        {
            "id": "61555349038001",
            "count": 19
        },
        {
            "id": "100079049570490",
            "count": 56
        },
        {
            "id": "100090867101623",
            "count": 30
        },
        {
            "id": "100043325152729",
            "count": 10
        },
        {
            "id": "100084479298103",
            "count": 40
        },
        {
            "id": "100046988973706",
            "count": 0
        },
        {
            "id": "61567265897789",
            "count": 1
        }
    ],
    "week": [
        {
            "id": "100065516136762",
            "count": 0,
            "name": "Lê Văn Thuận"
        },
        {
            "id": "61553962150623",
            "count": 61,
            "name": "Văn Đức"
        },
        {
            "id": "100093791194651",
            "count": 2,
            "name": "Tran Thi Tra My"
        },
        {
            "id": "100029891650673",
            "count": 0,
            "name": "Trịnh Ngọc Hà"
        },
        {
            "id": "1158392565",
            "count": 366,
            "name": "Miranda Wiebe"
        },
        {
            "id": "100002967609950",
            "count": 0,
            "name": "Istvan Kocsis"
        },
        {
            "id": "61566316212795",
            "count": 98,
            "name": "Thuc Vo"
        },
        {
            "id": "100090129305788",
            "count": 0,
            "name": "Ngọc Linh"
        },
        {
            "id": "100006936944673",
            "count": 0,
            "name": "Thanh Nhi"
        },
        {
            "id": "100078387196065",
            "count": 48,
            "name": "Thanh Tuấnn"
        },
        {
            "id": "100026964950417",
            "count": 31,
            "name": "Nguyễn Huỳnh"
        },
        {
            "id": "100045699785906",
            "count": 0,
            "name": "Trần Thị Hoài Thương"
        },
        {
            "id": "61555471987398",
            "count": 0,
            "name": "Kiều Thư"
        },
        {
            "id": "100080190861969",
            "count": 0,
            "name": "Minh Anh"
        },
        {
            "id": "100095363708552",
            "count": 0,
            "name": "Mai Nguyễn Văn Đạt"
        },
        {
            "id": "100005888041145",
            "count": 0,
            "name": "Lap Béo"
        },
        {
            "id": "100091429430126",
            "count": 0,
            "name": "Nguyễn Quốc Vũ"
        },
        {
            "id": "100034372458968",
            "count": 79,
            "name": "CaoXuân Công"
        },
        {
            "id": "100088357192531",
            "count": 12,
            "name": "Minh Mến"
        },
        {
            "id": "100082047108350",
            "count": 57,
            "name": "Lường Văn Trường"
        },
        {
            "id": "100061614405741",
            "count": 2,
            "name": "Ngọc Thư Ký"
        },
        {
            "id": "100065251602724",
            "count": 26,
            "name": "Phạm Văn Phúc"
        },
        {
            "id": "100086991830331",
            "count": 98,
            "name": "Đặng Thành"
        },
        {
            "id": "100072659419001",
            "count": 0,
            "name": "Vũ Đạt"
        },
        {
            "id": "100087208038222",
            "count": 4,
            "name": "Mun Trang"
        },
        {
            "id": "100063787487497",
            "count": 56,
            "name": "Trúc Thanh"
        },
        {
            "id": "100087957049611",
            "count": 306,
            "name": "Loan Dương"
        },
        {
            "id": "100024752473193",
            "count": 8,
            "name": "Nguyễn Vinh Tấn Phát"
        },
        {
            "id": "100093026747618",
            "count": 1,
            "name": "Hân Hân Ngọc"
        },
        {
            "id": "100083942956835",
            "count": 19,
            "name": "Thanh Tuyền"
        },
        {
            "id": "61554009424917",
            "count": 2,
            "name": "Quỳnh Ánh"
        },
        {
            "id": "100077289021351",
            "count": 0,
            "name": "Quang Huy"
        },
        {
            "id": "100087926503920",
            "count": 0,
            "name": "Lương Nhật Minh"
        },
        {
            "id": "61554712072326",
            "count": 4,
            "name": "Truong Thanh Dang"
        },
        {
            "id": "100039470115552",
            "count": 47,
            "name": "Ánh Thủy"
        },
        {
            "id": "61556481320309",
            "count": 47,
            "name": "Nguyễn Viết Trường"
        },
        {
            "id": "100089269775183",
            "count": 2,
            "name": "Mỹ Hoà"
        },
        {
            "id": "100020528575783",
            "count": 0,
            "name": "Ngô Tuấn Hà"
        },
        {
            "id": "100024133790484",
            "count": 0,
            "name": "Phii Bắp"
        },
        {
            "id": "100046292103991",
            "count": 36,
            "name": "Nguyễn Minh Anh"
        },
        {
            "id": "100028370918283",
            "count": 2,
            "name": "Đinh Văn Nghĩa"
        },
        {
            "id": "100072236886559",
            "count": 1,
            "name": "Phan Công Lý"
        },
        {
            "id": "1578092979",
            "count": 18,
            "name": "Ngô Tuấn Hà"
        },
        {
            "id": "100014679373226",
            "count": 1,
            "name": "Ngọc Cường"
        },
        {
            "id": "61566536774365",
            "count": 21,
            "name": "Nguyễn Thị Mỹ Ngọc"
        },
        {
            "id": "100065563803743",
            "count": 0,
            "name": "Thành Văn"
        },
        {
            "id": "100020953182001",
            "count": 0,
            "name": "Thu Hà"
        },
        {
            "id": "100034985235308",
            "count": 51,
            "name": "Đka Khang"
        },
        {
            "id": "100073619405321",
            "count": 48,
            "name": "Gia Hưng"
        },
        {
            "id": "100090989239372",
            "count": 1,
            "name": "Nhất Nhất"
        },
        {
            "id": "100088520275551",
            "count": 5,
            "name": "Duy Tuấn"
        },
        {
            "id": "100050284906760",
            "count": 8,
            "name": "Văn Banh"
        },
        {
            "id": "100088684481575",
            "count": 0,
            "name": "Nguyen DieuHa"
        },
        {
            "id": "100075683283542",
            "count": 0,
            "name": "Nguyễn Mạnh"
        },
        {
            "id": "100088285105412",
            "count": 4,
            "name": "Thanh Vânn"
        },
        {
            "id": "100084739688576",
            "count": 2,
            "name": "Nho Anh"
        },
        {
            "id": "100082452546345",
            "count": 2,
            "name": "Hongg Ngocc"
        },
        {
            "id": "61559416928399",
            "count": 1,
            "name": "Lê Thị Meo"
        },
        {
            "id": "100095397240263",
            "count": 51,
            "name": "Quế Trân"
        },
        {
            "id": "61555349038001",
            "count": 19
        },
        {
            "id": "100079049570490",
            "count": 56
        },
        {
            "id": "100090867101623",
            "count": 30
        },
        {
            "id": "100043325152729",
            "count": 10
        },
        {
            "id": "100084479298103",
            "count": 40
        },
        {
            "id": "100046988973706",
            "count": 0
        },
        {
            "id": "61567265897789",
            "count": 1
        }
    ],
    "day": [
        {
            "id": "100065516136762",
            "count": 0,
            "name": "Lê Văn Thuận"
        },
        {
            "id": "61553962150623",
            "count": 43,
            "name": "Văn Đức"
        },
        {
            "id": "100093791194651",
            "count": 1,
            "name": "Tran Thi Tra My"
        },
        {
            "id": "100029891650673",
            "count": 0,
            "name": "Trịnh Ngọc Hà"
        },
        {
            "id": "1158392565",
            "count": 220,
            "name": "Miranda Wiebe"
        },
        {
            "id": "100002967609950",
            "count": 0,
            "name": "Istvan Kocsis"
        },
        {
            "id": "61566316212795",
            "count": 70,
            "name": "Thuc Vo"
        },
        {
            "id": "100090129305788",
            "count": 0,
            "name": "Ngọc Linh"
        },
        {
            "id": "100006936944673",
            "count": 0,
            "name": "Thanh Nhi"
        },
        {
            "id": "100078387196065",
            "count": 28,
            "name": "Thanh Tuấnn"
        },
        {
            "id": "100026964950417",
            "count": 23,
            "name": "Nguyễn Huỳnh"
        },
        {
            "id": "100045699785906",
            "count": 0,
            "name": "Trần Thị Hoài Thương"
        },
        {
            "id": "61555471987398",
            "count": 0,
            "name": "Kiều Thư"
        },
        {
            "id": "100080190861969",
            "count": 0,
            "name": "Minh Anh"
        },
        {
            "id": "100095363708552",
            "count": 0,
            "name": "Mai Nguyễn Văn Đạt"
        },
        {
            "id": "100005888041145",
            "count": 0,
            "name": "Lap Béo"
        },
        {
            "id": "100091429430126",
            "count": 0,
            "name": "Nguyễn Quốc Vũ"
        },
        {
            "id": "100034372458968",
            "count": 41,
            "name": "CaoXuân Công"
        },
        {
            "id": "100088357192531",
            "count": 8,
            "name": "Minh Mến"
        },
        {
            "id": "100082047108350",
            "count": 55,
            "name": "Lường Văn Trường"
        },
        {
            "id": "100061614405741",
            "count": 2,
            "name": "Ngọc Thư Ký"
        },
        {
            "id": "100065251602724",
            "count": 14,
            "name": "Phạm Văn Phúc"
        },
        {
            "id": "100086991830331",
            "count": 12,
            "name": "Đặng Thành"
        },
        {
            "id": "100072659419001",
            "count": 0,
            "name": "Vũ Đạt"
        },
        {
            "id": "100087208038222",
            "count": 0,
            "name": "Mun Trang"
        },
        {
            "id": "100063787487497",
            "count": 27,
            "name": "Trúc Thanh"
        },
        {
            "id": "100087957049611",
            "count": 202,
            "name": "Loan Dương"
        },
        {
            "id": "100024752473193",
            "count": 5,
            "name": "Nguyễn Vinh Tấn Phát"
        },
        {
            "id": "100093026747618",
            "count": 0,
            "name": "Hân Hân Ngọc"
        },
        {
            "id": "100083942956835",
            "count": 13,
            "name": "Thanh Tuyền"
        },
        {
            "id": "61554009424917",
            "count": 0,
            "name": "Quỳnh Ánh"
        },
        {
            "id": "100077289021351",
            "count": 0,
            "name": "Quang Huy"
        },
        {
            "id": "100087926503920",
            "count": 0,
            "name": "Lương Nhật Minh"
        },
        {
            "id": "61554712072326",
            "count": 4,
            "name": "Truong Thanh Dang"
        },
        {
            "id": "100039470115552",
            "count": 2,
            "name": "Ánh Thủy"
        },
        {
            "id": "61556481320309",
            "count": 22,
            "name": "Nguyễn Viết Trường"
        },
        {
            "id": "100089269775183",
            "count": 1,
            "name": "Mỹ Hoà"
        },
        {
            "id": "100020528575783",
            "count": 0,
            "name": "Ngô Tuấn Hà"
        },
        {
            "id": "100024133790484",
            "count": 0,
            "name": "Phii Bắp"
        },
        {
            "id": "100046292103991",
            "count": 5,
            "name": "Nguyễn Minh Anh"
        },
        {
            "id": "100028370918283",
            "count": 2,
            "name": "Đinh Văn Nghĩa"
        },
        {
            "id": "100072236886559",
            "count": 0,
            "name": "Phan Công Lý"
        },
        {
            "id": "1578092979",
            "count": 2,
            "name": "Ngô Tuấn Hà"
        },
        {
            "id": "100014679373226",
            "count": 1,
            "name": "Ngọc Cường"
        },
        {
            "id": "61566536774365",
            "count": 15,
            "name": "Nguyễn Thị Mỹ Ngọc"
        },
        {
            "id": "100065563803743",
            "count": 0,
            "name": "Thành Văn"
        },
        {
            "id": "100020953182001",
            "count": 0,
            "name": "Thu Hà"
        },
        {
            "id": "100034985235308",
            "count": 28,
            "name": "Đka Khang"
        },
        {
            "id": "100073619405321",
            "count": 29,
            "name": "Gia Hưng"
        },
        {
            "id": "100090989239372",
            "count": 0,
            "name": "Nhất Nhất"
        },
        {
            "id": "100088520275551",
            "count": 0,
            "name": "Duy Tuấn"
        },
        {
            "id": "100050284906760",
            "count": 2,
            "name": "Văn Banh"
        },
        {
            "id": "100088684481575",
            "count": 0,
            "name": "Nguyen DieuHa"
        },
        {
            "id": "100075683283542",
            "count": 0,
            "name": "Nguyễn Mạnh"
        },
        {
            "id": "100088285105412",
            "count": 1,
            "name": "Thanh Vânn"
        },
        {
            "id": "100084739688576",
            "count": 2,
            "name": "Nho Anh"
        },
        {
            "id": "100082452546345",
            "count": 1,
            "name": "Hongg Ngocc"
        },
        {
            "id": "61559416928399",
            "count": 0,
            "name": "Lê Thị Meo"
        },
        {
            "id": "100095397240263",
            "count": 19,
            "name": "Quế Trân"
        },
        {
            "id": "61555349038001",
            "count": 0,
            "name": "Vu Bu La Thich"
        },
        {
            "id": "100079049570490",
            "count": 36,
            "name": "Trần Hoàng"
        },
        {
            "id": "100090867101623",
            "count": 30
        },
        {
            "id": "100043325152729",
            "count": 10
        },
        {
            "id": "100084479298103",
            "count": 40
        },
        {
            "id": "100046988973706",
            "count": 0
        },
        {
            "id": "61567265897789",
            "count": 1
        }
    ],
    "time": 2,
    "last": {
        "time": 6,
        "day": [
            {
                "id": "61557640501920",
                "count": 0
            },
            {
                "id": "100013837723514",
                "count": 0
            },
            {
                "id": "100063985268691",
                "count": 0
            },
            {
                "id": "100032253373259",
                "count": 0
            },
            {
                "id": "100009953310465",
                "count": 0
            },
            {
                "id": "100004916470514",
                "count": 0
            },
            {
                "id": "61556417147616",
                "count": 0
            },
            {
                "id": "100095106530419",
                "count": 0
            },
            {
                "id": "100068223827433",
                "count": 0
            },
            {
                "id": "100077039040393",
                "count": 0
            },
            {
                "id": "100031162012333",
                "count": 0
            },
            {
                "id": "100064140874327",
                "count": 0
            },
            {
                "id": "100017664844145",
                "count": 0
            },
            {
                "id": "100065516136762",
                "count": 0
            },
            {
                "id": "61557236371107",
                "count": 0
            },
            {
                "id": "100065103737065",
                "count": 0
            },
            {
                "id": "100036249213440",
                "count": 0
            },
            {
                "id": "100081555788428",
                "count": 0
            },
            {
                "id": "100049425472843",
                "count": 0
            },
            {
                "id": "61553661921100",
                "count": 0
            },
            {
                "id": "100052366790265",
                "count": 0
            },
            {
                "id": "100074857451571",
                "count": 0
            },
            {
                "id": "61564020185515",
                "count": 0
            },
            {
                "id": "61560258893080",
                "count": 0
            },
            {
                "id": "100064569581817",
                "count": 0
            },
            {
                "id": "100021952328732",
                "count": 0
            },
            {
                "id": "100078861940713",
                "count": 0
            },
            {
                "id": "100043538510098",
                "count": 0
            },
            {
                "id": "100079146220260",
                "count": 0
            },
            {
                "id": "100027529390587",
                "count": 0
            },
            {
                "id": "100083153254463",
                "count": 0
            },
            {
                "id": "100069261545017",
                "count": 0
            },
            {
                "id": "100086936477891",
                "count": 0
            },
            {
                "id": "61553962150623",
                "count": 0
            },
            {
                "id": "100028255478328",
                "count": 0
            },
            {
                "id": "100087656605207",
                "count": 0
            },
            {
                "id": "100044580577008",
                "count": 0
            },
            {
                "id": "100066455378425",
                "count": 0
            },
            {
                "id": "61550108905012",
                "count": 0
            },
            {
                "id": "100092213658040",
                "count": 0
            },
            {
                "id": "100079312520267",
                "count": 0
            },
            {
                "id": "100084362740349",
                "count": 0
            },
            {
                "id": "100041027286708",
                "count": 0
            },
            {
                "id": "100087565004425",
                "count": 0
            },
            {
                "id": "100009589523145",
                "count": 0
            },
            {
                "id": "61552481287097",
                "count": 0
            },
            {
                "id": "61553883668620",
                "count": 0
            },
            {
                "id": "100081858086684",
                "count": 0
            },
            {
                "id": "100032743312322",
                "count": 0
            },
            {
                "id": "100071659126730",
                "count": 0
            },
            {
                "id": "100057699069976",
                "count": 0
            },
            {
                "id": "100034523717638",
                "count": 0
            },
            {
                "id": "100046934884348",
                "count": 0
            },
            {
                "id": "100040221441586",
                "count": 0
            },
            {
                "id": "100074362784865",
                "count": 0
            },
            {
                "id": "100061487201929",
                "count": 0
            },
            {
                "id": "100010564806503",
                "count": 0
            },
            {
                "id": "100035751584911",
                "count": 0
            },
            {
                "id": "100093791194651",
                "count": 0
            },
            {
                "id": "100071656162209",
                "count": 0
            },
            {
                "id": "100070027331041",
                "count": 0
            },
            {
                "id": "100082599902138",
                "count": 0
            },
            {
                "id": "100079340187350",
                "count": 0
            },
            {
                "id": "100031338551604",
                "count": 0
            },
            {
                "id": "100065667583223",
                "count": 0
            },
            {
                "id": "100079193190730",
                "count": 0
            },
            {
                "id": "61566246339876",
                "count": 0
            },
            {
                "id": "100005878204204",
                "count": 0
            },
            {
                "id": "100071530341630",
                "count": 0
            },
            {
                "id": "100004460614127",
                "count": 0
            },
            {
                "id": "100026551324277",
                "count": 0
            },
            {
                "id": "100029891650673",
                "count": 0
            },
            {
                "id": "1158392565",
                "count": 0
            },
            {
                "id": "100056539762249",
                "count": 0
            },
            {
                "id": "61556929403491",
                "count": 0
            },
            {
                "id": "100068314185659",
                "count": 0
            },
            {
                "id": "100030983321581",
                "count": 0
            },
            {
                "id": "100017744312019",
                "count": 0
            },
            {
                "id": "100000501658632",
                "count": 0
            },
            {
                "id": "100005976004976",
                "count": 0
            },
            {
                "id": "100009967233840",
                "count": 0
            },
            {
                "id": "100002967609950",
                "count": 0
            },
            {
                "id": "100078923949851",
                "count": 0
            },
            {
                "id": "61566316212795",
                "count": 0
            },
            {
                "id": "100024601743239",
                "count": 0
            },
            {
                "id": "100013350946731",
                "count": 0
            },
            {
                "id": "100078459223013",
                "count": 0
            },
            {
                "id": "100028958234075",
                "count": 0
            },
            {
                "id": "61564500608611",
                "count": 0
            },
            {
                "id": "61557291830971",
                "count": 0
            },
            {
                "id": "61557929296665",
                "count": 0
            },
            {
                "id": "100067452935445",
                "count": 0
            },
            {
                "id": "100081830474021",
                "count": 0
            },
            {
                "id": "100038807896160",
                "count": 0
            },
            {
                "id": "61559219800503",
                "count": 0
            },
            {
                "id": "100071622855785",
                "count": 0
            },
            {
                "id": "100046770393349",
                "count": 0
            },
            {
                "id": "100027527825462",
                "count": 0
            },
            {
                "id": "100085696175951",
                "count": 0
            },
            {
                "id": "100089127767527",
                "count": 0
            },
            {
                "id": "100038883451865",
                "count": 0
            },
            {
                "id": "100033091910235",
                "count": 0
            },
            {
                "id": "100048203239441",
                "count": 0
            },
            {
                "id": "100079616524715",
                "count": 0
            },
            {
                "id": "100070626513816",
                "count": 0
            },
            {
                "id": "100076296349475",
                "count": 0
            },
            {
                "id": "100040261761468",
                "count": 0
            },
            {
                "id": "61563927247552",
                "count": 0
            },
            {
                "id": "100010919689005",
                "count": 0
            },
            {
                "id": "61556010158353",
                "count": 0
            },
            {
                "id": "100034032130864",
                "count": 0
            },
            {
                "id": "100049802465659",
                "count": 0
            },
            {
                "id": "100047447352337",
                "count": 0
            },
            {
                "id": "100055111146222",
                "count": 0
            },
            {
                "id": "100091131411685",
                "count": 0
            },
            {
                "id": "100029219033315",
                "count": 0
            },
            {
                "id": "100088266270606",
                "count": 0
            },
            {
                "id": "100084370203781",
                "count": 0
            },
            {
                "id": "100054501622159",
                "count": 0
            },
            {
                "id": "100039565813965",
                "count": 0
            },
            {
                "id": "100089815886127",
                "count": 0
            },
            {
                "id": "100014748675872",
                "count": 0
            },
            {
                "id": "100036259792896",
                "count": 0
            },
            {
                "id": "61555338494821",
                "count": 0
            },
            {
                "id": "100012690334441",
                "count": 0
            },
            {
                "id": "100040031657581",
                "count": 0
            },
            {
                "id": "61564660623762",
                "count": 0
            },
            {
                "id": "100065255672551",
                "count": 0
            },
            {
                "id": "100007143879321",
                "count": 0
            },
            {
                "id": "100073268376242",
                "count": 0
            },
            {
                "id": "100039560477639",
                "count": 0
            },
            {
                "id": "100046414267582",
                "count": 0
            },
            {
                "id": "100067905001614",
                "count": 0
            },
            {
                "id": "100011766365674",
                "count": 0
            },
            {
                "id": "100082064498628",
                "count": 0
            },
            {
                "id": "100073740078426",
                "count": 0
            },
            {
                "id": "100072540013754",
                "count": 0
            },
            {
                "id": "100066920820047",
                "count": 0
            },
            {
                "id": "100058940613760",
                "count": 0
            },
            {
                "id": "100028492743649",
                "count": 0
            },
            {
                "id": "61556831713793",
                "count": 0
            },
            {
                "id": "100070995965489",
                "count": 0
            },
            {
                "id": "61556505569045",
                "count": 0
            },
            {
                "id": "100039470115552",
                "count": 0
            },
            {
                "id": "100079519164962",
                "count": 0
            },
            {
                "id": "100090129305788",
                "count": 0
            },
            {
                "id": "100084154012986",
                "count": 0
            },
            {
                "id": "100006936944673",
                "count": 0
            },
            {
                "id": "100036055448584",
                "count": 0
            },
            {
                "id": "100043737220812",
                "count": 0
            },
            {
                "id": "61557354486365",
                "count": 0
            },
            {
                "id": "100025809166947",
                "count": 0
            },
            {
                "id": "100063763835697",
                "count": 0
            },
            {
                "id": "100037465537146",
                "count": 0
            },
            {
                "id": "100090438733490",
                "count": 0
            },
            {
                "id": "100078387196065",
                "count": 0
            },
            {
                "id": "100084060151027",
                "count": 0
            },
            {
                "id": "100027049928020",
                "count": 0
            },
            {
                "id": "100076032724777",
                "count": 0
            },
            {
                "id": "100094362468397",
                "count": 0
            },
            {
                "id": "100021815657778",
                "count": 0
            },
            {
                "id": "100095555281347",
                "count": 0
            },
            {
                "id": "100077505227319",
                "count": 0
            },
            {
                "id": "100056068089327",
                "count": 0
            },
            {
                "id": "61560726602950",
                "count": 0
            },
            {
                "id": "100042872836916",
                "count": 0
            },
            {
                "id": "61566931694865",
                "count": 0
            },
            {
                "id": "100026964950417",
                "count": 0
            },
            {
                "id": "100070649401642",
                "count": 0
            },
            {
                "id": "100012764686553",
                "count": 0
            },
            {
                "id": "61556152177462",
                "count": 0
            },
            {
                "id": "100052968673523",
                "count": 0
            },
            {
                "id": "100022249714707",
                "count": 0
            },
            {
                "id": "100021962049476",
                "count": 0
            },
            {
                "id": "100048331443728",
                "count": 0
            },
            {
                "id": "100062258945566",
                "count": 0
            },
            {
                "id": "61566409856236",
                "count": 0
            },
            {
                "id": "100088965211540",
                "count": 0
            },
            {
                "id": "100090976310225",
                "count": 0
            },
            {
                "id": "100086602639961",
                "count": 0
            },
            {
                "id": "100027916592808",
                "count": 0
            },
            {
                "id": "100077633127097",
                "count": 0
            },
            {
                "id": "100045699785906",
                "count": 0
            },
            {
                "id": "61555471987398",
                "count": 0
            },
            {
                "id": "100074885508444",
                "count": 0
            },
            {
                "id": "61550624985594",
                "count": 0
            },
            {
                "id": "100080877691073",
                "count": 0
            },
            {
                "id": "100074686485074",
                "count": 0
            },
            {
                "id": "100058759502298",
                "count": 0
            },
            {
                "id": "100048420243949",
                "count": 0
            },
            {
                "id": "100080190861969",
                "count": 0
            },
            {
                "id": "100034906807947",
                "count": 0
            },
            {
                "id": "100088703403974",
                "count": 0
            },
            {
                "id": "61553611596032",
                "count": 0
            },
            {
                "id": "100095363708552",
                "count": 0
            },
            {
                "id": "100073756837808",
                "count": 0
            },
            {
                "id": "100052222875985",
                "count": 0
            },
            {
                "id": "100005888041145",
                "count": 0
            },
            {
                "id": "100044871664655",
                "count": 0
            },
            {
                "id": "100094419804425",
                "count": 0
            },
            {
                "id": "100087465501146",
                "count": 0
            },
            {
                "id": "100003898928573",
                "count": 0
            },
            {
                "id": "100080129897029",
                "count": 0
            },
            {
                "id": "100091429430126",
                "count": 0
            },
            {
                "id": "100028731513589",
                "count": 0
            },
            {
                "id": "61555805965764",
                "count": 0
            },
            {
                "id": "100061614405741",
                "count": 0
            },
            {
                "id": "100057169110632",
                "count": 0
            },
            {
                "id": "100038162797640",
                "count": 0
            },
            {
                "id": "100033789613121",
                "count": 0
            },
            {
                "id": "100045306844811",
                "count": 0
            },
            {
                "id": "100068084602829",
                "count": 0
            },
            {
                "id": "100079049570490",
                "count": 0
            },
            {
                "id": "100087957049611",
                "count": 0
            },
            {
                "id": "100031367150362",
                "count": 0
            },
            {
                "id": "100034372458968",
                "count": 0
            },
            {
                "id": "61556481320309",
                "count": 0
            },
            {
                "id": "100056215040358",
                "count": 0
            },
            {
                "id": "100078999342847",
                "count": 0
            },
            {
                "id": "100088357192531",
                "count": 0
            },
            {
                "id": "61550358475858",
                "count": 0
            },
            {
                "id": "100049934205450",
                "count": 0
            },
            {
                "id": "100034981236060",
                "count": 0
            },
            {
                "id": "100004236194656",
                "count": 0
            },
            {
                "id": "61563069090453",
                "count": 0
            },
            {
                "id": "100061191476657",
                "count": 0
            },
            {
                "id": "100073526257582",
                "count": 0
            },
            {
                "id": "100012010846718",
                "count": 0
            },
            {
                "id": "100008889529028",
                "count": 0
            },
            {
                "id": "100082047108350",
                "count": 0
            },
            {
                "id": "100084941397068",
                "count": 0
            },
            {
                "id": "100024752473193",
                "count": 0
            },
            {
                "id": "100072050832041",
                "count": 0
            },
            {
                "id": "61551350656545",
                "count": 0
            },
            {
                "id": "100091071605012",
                "count": 0
            },
            {
                "id": "100070338754399",
                "count": 0
            },
            {
                "id": "100094588632612",
                "count": 0
            },
            {
                "id": "100035026651106",
                "count": 0
            },
            {
                "id": "100065251602724",
                "count": 0
            },
            {
                "id": "61556252904168",
                "count": 0
            },
            {
                "id": "100052326488654",
                "count": 0
            },
            {
                "id": "100086991830331",
                "count": 0
            },
            {
                "id": "100093913730541",
                "count": 0
            },
            {
                "id": "100064282453501",
                "count": 0
            },
            {
                "id": "100086521542999",
                "count": 0
            },
            {
                "id": "100060466302704",
                "count": 0
            },
            {
                "id": "100030712594010",
                "count": 0
            },
            {
                "id": "100068981859755",
                "count": 0
            },
            {
                "id": "100076801902276",
                "count": 0
            },
            {
                "id": "61554505697690",
                "count": 0
            },
            {
                "id": "100000574813002",
                "count": 0
            },
            {
                "id": "61552595601359",
                "count": 0
            },
            {
                "id": "100036071297552",
                "count": 0
            },
            {
                "id": "100072659419001",
                "count": 0
            },
            {
                "id": "100040558276592",
                "count": 0
            },
            {
                "id": "100030661180098",
                "count": 0
            },
            {
                "id": "100078923513348",
                "count": 0
            },
            {
                "id": "100041885615110",
                "count": 0
            },
            {
                "id": "61550877991661",
                "count": 0
            },
            {
                "id": "100034645192868",
                "count": 0
            },
            {
                "id": "100084260606796",
                "count": 0
            },
            {
                "id": "100037604047018",
                "count": 0
            },
            {
                "id": "100087208038222",
                "count": 0
            },
            {
                "id": "100044497115675",
                "count": 0
            },
            {
                "id": "100023337000977",
                "count": 0
            },
            {
                "id": "100072860617426",
                "count": 0
            },
            {
                "id": "100014359039134",
                "count": 0
            },
            {
                "id": "100009793391816",
                "count": 0
            },
            {
                "id": "61564142953855",
                "count": 0
            },
            {
                "id": "100063787487497",
                "count": 0
            },
            {
                "id": "100080149855973",
                "count": 0
            },
            {
                "id": "100093325924420",
                "count": 0
            },
            {
                "id": "100038988972012",
                "count": 0
            },
            {
                "id": "100075513960894",
                "count": 0
            },
            {
                "id": "100038398534000",
                "count": 0
            },
            {
                "id": "61564170421535",
                "count": 0
            },
            {
                "id": "100078032562902",
                "count": 0
            },
            {
                "id": "61562187969494",
                "count": 0
            },
            {
                "id": "100093026747618",
                "count": 0
            },
            {
                "id": "100083942956835",
                "count": 0
            },
            {
                "id": "61554009424917",
                "count": 0
            },
            {
                "id": "61555847747044",
                "count": 0
            },
            {
                "id": "100086112716372",
                "count": 0
            },
            {
                "id": "100077289021351",
                "count": 0
            },
            {
                "id": "100087926503920",
                "count": 0
            },
            {
                "id": "100035628160194",
                "count": 0
            },
            {
                "id": "100050811503608",
                "count": 0
            },
            {
                "id": "100020528575783",
                "count": 0
            },
            {
                "id": "100095199310624",
                "count": 0
            },
            {
                "id": "100083304116208",
                "count": 0
            },
            {
                "id": "61554712072326",
                "count": 0
            },
            {
                "id": "100032049042314",
                "count": 0
            },
            {
                "id": "100093139814659",
                "count": 0
            },
            {
                "id": "100091325948910",
                "count": 0
            },
            {
                "id": "100092123136990",
                "count": 0
            },
            {
                "id": "100094102604190",
                "count": 0
            },
            {
                "id": "100077300294092",
                "count": 0
            },
            {
                "id": "100059101635841",
                "count": 0
            },
            {
                "id": "61556989617236",
                "count": 0
            },
            {
                "id": "100089269775183",
                "count": 0
            },
            {
                "id": "61554993582294",
                "count": 0
            },
            {
                "id": "100024133790484",
                "count": 0
            },
            {
                "id": "100092873784120",
                "count": 0
            },
            {
                "id": "100046292103991",
                "count": 0
            },
            {
                "id": "100028370918283",
                "count": 0
            },
            {
                "id": "100037865107893",
                "count": 0
            },
            {
                "id": "100070006783724",
                "count": 0
            },
            {
                "id": "100072236886559",
                "count": 0
            },
            {
                "id": "1578092979",
                "count": 0
            },
            {
                "id": "61553598653900",
                "count": 0
            },
            {
                "id": "100014679373226",
                "count": 0
            },
            {
                "id": "61568461416340",
                "count": 0
            },
            {
                "id": "100060796074174",
                "count": 0
            },
            {
                "id": "61566536774365",
                "count": 0
            },
            {
                "id": "100065563803743",
                "count": 0
            },
            {
                "id": "100080963384222",
                "count": 0
            },
            {
                "id": "100050590212254",
                "count": 0
            },
            {
                "id": "100020953182001",
                "count": 0
            },
            {
                "id": "100034985235308",
                "count": 0
            },
            {
                "id": "100073619405321",
                "count": 0
            },
            {
                "id": "100073677096216",
                "count": 0
            },
            {
                "id": "100095397240263",
                "count": 0
            },
            {
                "id": "100090989239372",
                "count": 0
            },
            {
                "id": "61556386283339",
                "count": 0
            },
            {
                "id": "100051223639760",
                "count": 0
            },
            {
                "id": "100088520275551",
                "count": 0
            },
            {
                "id": "100086552163685",
                "count": 0
            },
            {
                "id": "100050284906760",
                "count": 0
            },
            {
                "id": "100088684481575",
                "count": 0
            },
            {
                "id": "100075683283542",
                "count": 0
            },
            {
                "id": "100088285105412",
                "count": 0
            },
            {
                "id": "100084739688576",
                "count": 0
            },
            {
                "id": "100082452546345",
                "count": 0
            },
            {
                "id": "61559416928399",
                "count": 0
            },
            {
                "id": "61555349038001",
                "count": 0
            },
            {
                "id": "100090867101623",
                "count": 0
            },
            {
                "id": "100088947663299",
                "count": 0
            },
            {
                "id": "100043325152729",
                "count": 0
            },
            {
                "id": "100084479298103",
                "count": 0
            },
            {
                "id": "100046988973706",
                "count": 0
            },
            {
                "id": "61567265897789",
                "count": 0
            }
        ],
        "week": [
            {
                "id": "61557640501920",
                "count": 0
            },
            {
                "id": "100013837723514",
                "count": 0
            },
            {
                "id": "100063985268691",
                "count": 0
            },
            {
                "id": "100032253373259",
                "count": 0
            },
            {
                "id": "100009953310465",
                "count": 0
            },
            {
                "id": "100004916470514",
                "count": 0
            },
            {
                "id": "61556417147616",
                "count": 0
            },
            {
                "id": "100095106530419",
                "count": 0
            },
            {
                "id": "100068223827433",
                "count": 0
            },
            {
                "id": "100077039040393",
                "count": 0
            },
            {
                "id": "100031162012333",
                "count": 0
            },
            {
                "id": "100064140874327",
                "count": 0
            },
            {
                "id": "100017664844145",
                "count": 0
            },
            {
                "id": "100065516136762",
                "count": 0
            },
            {
                "id": "61557236371107",
                "count": 0
            },
            {
                "id": "100065103737065",
                "count": 0
            },
            {
                "id": "100036249213440",
                "count": 0
            },
            {
                "id": "100081555788428",
                "count": 0
            },
            {
                "id": "100049425472843",
                "count": 0
            },
            {
                "id": "61553661921100",
                "count": 0
            },
            {
                "id": "100052366790265",
                "count": 0
            },
            {
                "id": "100074857451571",
                "count": 0
            },
            {
                "id": "61564020185515",
                "count": 0
            },
            {
                "id": "61560258893080",
                "count": 0
            },
            {
                "id": "100064569581817",
                "count": 0
            },
            {
                "id": "100021952328732",
                "count": 0
            },
            {
                "id": "100078861940713",
                "count": 0
            },
            {
                "id": "100043538510098",
                "count": 0
            },
            {
                "id": "100079146220260",
                "count": 0
            },
            {
                "id": "100027529390587",
                "count": 0
            },
            {
                "id": "100083153254463",
                "count": 0
            },
            {
                "id": "100069261545017",
                "count": 0
            },
            {
                "id": "100086936477891",
                "count": 0
            },
            {
                "id": "61553962150623",
                "count": 0
            },
            {
                "id": "100028255478328",
                "count": 0
            },
            {
                "id": "100087656605207",
                "count": 0
            },
            {
                "id": "100044580577008",
                "count": 0
            },
            {
                "id": "100066455378425",
                "count": 0
            },
            {
                "id": "61550108905012",
                "count": 0
            },
            {
                "id": "100092213658040",
                "count": 0
            },
            {
                "id": "100079312520267",
                "count": 0
            },
            {
                "id": "100084362740349",
                "count": 0
            },
            {
                "id": "100041027286708",
                "count": 0
            },
            {
                "id": "100087565004425",
                "count": 0
            },
            {
                "id": "100009589523145",
                "count": 0
            },
            {
                "id": "61552481287097",
                "count": 0
            },
            {
                "id": "61553883668620",
                "count": 0
            },
            {
                "id": "100081858086684",
                "count": 0
            },
            {
                "id": "100032743312322",
                "count": 0
            },
            {
                "id": "100071659126730",
                "count": 0
            },
            {
                "id": "100057699069976",
                "count": 0
            },
            {
                "id": "100034523717638",
                "count": 0
            },
            {
                "id": "100046934884348",
                "count": 0
            },
            {
                "id": "100040221441586",
                "count": 0
            },
            {
                "id": "100074362784865",
                "count": 0
            },
            {
                "id": "100061487201929",
                "count": 0
            },
            {
                "id": "100010564806503",
                "count": 0
            },
            {
                "id": "100035751584911",
                "count": 0
            },
            {
                "id": "100093791194651",
                "count": 0
            },
            {
                "id": "100071656162209",
                "count": 0
            },
            {
                "id": "100070027331041",
                "count": 0
            },
            {
                "id": "100082599902138",
                "count": 0
            },
            {
                "id": "100079340187350",
                "count": 0
            },
            {
                "id": "100031338551604",
                "count": 0
            },
            {
                "id": "100065667583223",
                "count": 0
            },
            {
                "id": "100079193190730",
                "count": 0
            },
            {
                "id": "61566246339876",
                "count": 0
            },
            {
                "id": "100005878204204",
                "count": 0
            },
            {
                "id": "100071530341630",
                "count": 0
            },
            {
                "id": "100004460614127",
                "count": 0
            },
            {
                "id": "100026551324277",
                "count": 0
            },
            {
                "id": "100029891650673",
                "count": 0
            },
            {
                "id": "1158392565",
                "count": 0
            },
            {
                "id": "100056539762249",
                "count": 0
            },
            {
                "id": "61556929403491",
                "count": 0
            },
            {
                "id": "100068314185659",
                "count": 0
            },
            {
                "id": "100030983321581",
                "count": 0
            },
            {
                "id": "100017744312019",
                "count": 0
            },
            {
                "id": "100000501658632",
                "count": 0
            },
            {
                "id": "100005976004976",
                "count": 0
            },
            {
                "id": "100009967233840",
                "count": 0
            },
            {
                "id": "100002967609950",
                "count": 0
            },
            {
                "id": "100078923949851",
                "count": 0
            },
            {
                "id": "61566316212795",
                "count": 0
            },
            {
                "id": "100024601743239",
                "count": 0
            },
            {
                "id": "100013350946731",
                "count": 0
            },
            {
                "id": "100078459223013",
                "count": 0
            },
            {
                "id": "100028958234075",
                "count": 0
            },
            {
                "id": "61564500608611",
                "count": 0
            },
            {
                "id": "61557291830971",
                "count": 0
            },
            {
                "id": "61557929296665",
                "count": 0
            },
            {
                "id": "100067452935445",
                "count": 0
            },
            {
                "id": "100081830474021",
                "count": 0
            },
            {
                "id": "100038807896160",
                "count": 0
            },
            {
                "id": "61559219800503",
                "count": 0
            },
            {
                "id": "100071622855785",
                "count": 0
            },
            {
                "id": "100046770393349",
                "count": 0
            },
            {
                "id": "100027527825462",
                "count": 0
            },
            {
                "id": "100085696175951",
                "count": 0
            },
            {
                "id": "100089127767527",
                "count": 0
            },
            {
                "id": "100038883451865",
                "count": 0
            },
            {
                "id": "100033091910235",
                "count": 0
            },
            {
                "id": "100048203239441",
                "count": 0
            },
            {
                "id": "100079616524715",
                "count": 0
            },
            {
                "id": "100070626513816",
                "count": 0
            },
            {
                "id": "100076296349475",
                "count": 0
            },
            {
                "id": "100040261761468",
                "count": 0
            },
            {
                "id": "61563927247552",
                "count": 0
            },
            {
                "id": "100010919689005",
                "count": 0
            },
            {
                "id": "61556010158353",
                "count": 0
            },
            {
                "id": "100034032130864",
                "count": 0
            },
            {
                "id": "100049802465659",
                "count": 0
            },
            {
                "id": "100047447352337",
                "count": 0
            },
            {
                "id": "100055111146222",
                "count": 0
            },
            {
                "id": "100091131411685",
                "count": 0
            },
            {
                "id": "100029219033315",
                "count": 0
            },
            {
                "id": "100088266270606",
                "count": 0
            },
            {
                "id": "100084370203781",
                "count": 0
            },
            {
                "id": "100054501622159",
                "count": 0
            },
            {
                "id": "100039565813965",
                "count": 0
            },
            {
                "id": "100089815886127",
                "count": 0
            },
            {
                "id": "100014748675872",
                "count": 0
            },
            {
                "id": "100036259792896",
                "count": 0
            },
            {
                "id": "61555338494821",
                "count": 0
            },
            {
                "id": "100012690334441",
                "count": 0
            },
            {
                "id": "100040031657581",
                "count": 0
            },
            {
                "id": "61564660623762",
                "count": 0
            },
            {
                "id": "100065255672551",
                "count": 0
            },
            {
                "id": "100007143879321",
                "count": 0
            },
            {
                "id": "100073268376242",
                "count": 0
            },
            {
                "id": "100039560477639",
                "count": 0
            },
            {
                "id": "100046414267582",
                "count": 0
            },
            {
                "id": "100067905001614",
                "count": 0
            },
            {
                "id": "100011766365674",
                "count": 0
            },
            {
                "id": "100082064498628",
                "count": 0
            },
            {
                "id": "100073740078426",
                "count": 0
            },
            {
                "id": "100072540013754",
                "count": 0
            },
            {
                "id": "100066920820047",
                "count": 0
            },
            {
                "id": "100058940613760",
                "count": 0
            },
            {
                "id": "100028492743649",
                "count": 0
            },
            {
                "id": "61556831713793",
                "count": 0
            },
            {
                "id": "100070995965489",
                "count": 0
            },
            {
                "id": "61556505569045",
                "count": 0
            },
            {
                "id": "100039470115552",
                "count": 0
            },
            {
                "id": "100079519164962",
                "count": 0
            },
            {
                "id": "100090129305788",
                "count": 0
            },
            {
                "id": "100084154012986",
                "count": 0
            },
            {
                "id": "100006936944673",
                "count": 0
            },
            {
                "id": "100036055448584",
                "count": 0
            },
            {
                "id": "100043737220812",
                "count": 0
            },
            {
                "id": "61557354486365",
                "count": 0
            },
            {
                "id": "100025809166947",
                "count": 0
            },
            {
                "id": "100063763835697",
                "count": 0
            },
            {
                "id": "100037465537146",
                "count": 0
            },
            {
                "id": "100090438733490",
                "count": 0
            },
            {
                "id": "100078387196065",
                "count": 0
            },
            {
                "id": "100084060151027",
                "count": 0
            },
            {
                "id": "100027049928020",
                "count": 0
            },
            {
                "id": "100076032724777",
                "count": 0
            },
            {
                "id": "100094362468397",
                "count": 0
            },
            {
                "id": "100021815657778",
                "count": 0
            },
            {
                "id": "100095555281347",
                "count": 0
            },
            {
                "id": "100077505227319",
                "count": 0
            },
            {
                "id": "100056068089327",
                "count": 0
            },
            {
                "id": "61560726602950",
                "count": 0
            },
            {
                "id": "100042872836916",
                "count": 0
            },
            {
                "id": "61566931694865",
                "count": 0
            },
            {
                "id": "100026964950417",
                "count": 0
            },
            {
                "id": "100070649401642",
                "count": 0
            },
            {
                "id": "100012764686553",
                "count": 0
            },
            {
                "id": "61556152177462",
                "count": 0
            },
            {
                "id": "100052968673523",
                "count": 0
            },
            {
                "id": "100022249714707",
                "count": 0
            },
            {
                "id": "100021962049476",
                "count": 0
            },
            {
                "id": "100048331443728",
                "count": 0
            },
            {
                "id": "100062258945566",
                "count": 0
            },
            {
                "id": "61566409856236",
                "count": 0
            },
            {
                "id": "100088965211540",
                "count": 0
            },
            {
                "id": "100090976310225",
                "count": 0
            },
            {
                "id": "100086602639961",
                "count": 0
            },
            {
                "id": "100027916592808",
                "count": 0
            },
            {
                "id": "100077633127097",
                "count": 0
            },
            {
                "id": "100045699785906",
                "count": 0
            },
            {
                "id": "61555471987398",
                "count": 0
            },
            {
                "id": "100074885508444",
                "count": 0
            },
            {
                "id": "61550624985594",
                "count": 0
            },
            {
                "id": "100080877691073",
                "count": 0
            },
            {
                "id": "100074686485074",
                "count": 0
            },
            {
                "id": "100058759502298",
                "count": 0
            },
            {
                "id": "100048420243949",
                "count": 0
            },
            {
                "id": "100080190861969",
                "count": 0
            },
            {
                "id": "100034906807947",
                "count": 0
            },
            {
                "id": "100088703403974",
                "count": 0
            },
            {
                "id": "61553611596032",
                "count": 0
            },
            {
                "id": "100095363708552",
                "count": 0
            },
            {
                "id": "100073756837808",
                "count": 0
            },
            {
                "id": "100052222875985",
                "count": 0
            },
            {
                "id": "100005888041145",
                "count": 0
            },
            {
                "id": "100044871664655",
                "count": 0
            },
            {
                "id": "100094419804425",
                "count": 0
            },
            {
                "id": "100087465501146",
                "count": 0
            },
            {
                "id": "100003898928573",
                "count": 0
            },
            {
                "id": "100080129897029",
                "count": 0
            },
            {
                "id": "100091429430126",
                "count": 0
            },
            {
                "id": "100028731513589",
                "count": 0
            },
            {
                "id": "61555805965764",
                "count": 0
            },
            {
                "id": "100061614405741",
                "count": 0
            },
            {
                "id": "100057169110632",
                "count": 0
            },
            {
                "id": "100038162797640",
                "count": 0
            },
            {
                "id": "100033789613121",
                "count": 0
            },
            {
                "id": "100045306844811",
                "count": 0
            },
            {
                "id": "100068084602829",
                "count": 0
            },
            {
                "id": "100079049570490",
                "count": 0
            },
            {
                "id": "100087957049611",
                "count": 0
            },
            {
                "id": "100031367150362",
                "count": 0
            },
            {
                "id": "100034372458968",
                "count": 0
            },
            {
                "id": "61556481320309",
                "count": 0
            },
            {
                "id": "100056215040358",
                "count": 0
            },
            {
                "id": "100078999342847",
                "count": 0
            },
            {
                "id": "100088357192531",
                "count": 0
            },
            {
                "id": "61550358475858",
                "count": 0
            },
            {
                "id": "100049934205450",
                "count": 0
            },
            {
                "id": "100034981236060",
                "count": 0
            },
            {
                "id": "100004236194656",
                "count": 0
            },
            {
                "id": "61563069090453",
                "count": 0
            },
            {
                "id": "100061191476657",
                "count": 0
            },
            {
                "id": "100073526257582",
                "count": 0
            },
            {
                "id": "100012010846718",
                "count": 0
            },
            {
                "id": "100008889529028",
                "count": 0
            },
            {
                "id": "100082047108350",
                "count": 0
            },
            {
                "id": "100084941397068",
                "count": 0
            },
            {
                "id": "100024752473193",
                "count": 0
            },
            {
                "id": "100072050832041",
                "count": 0
            },
            {
                "id": "61551350656545",
                "count": 0
            },
            {
                "id": "100091071605012",
                "count": 0
            },
            {
                "id": "100070338754399",
                "count": 0
            },
            {
                "id": "100094588632612",
                "count": 0
            },
            {
                "id": "100035026651106",
                "count": 0
            },
            {
                "id": "100065251602724",
                "count": 0
            },
            {
                "id": "61556252904168",
                "count": 0
            },
            {
                "id": "100052326488654",
                "count": 0
            },
            {
                "id": "100086991830331",
                "count": 0
            },
            {
                "id": "100093913730541",
                "count": 0
            },
            {
                "id": "100064282453501",
                "count": 0
            },
            {
                "id": "100086521542999",
                "count": 0
            },
            {
                "id": "100060466302704",
                "count": 0
            },
            {
                "id": "100030712594010",
                "count": 0
            },
            {
                "id": "100068981859755",
                "count": 0
            },
            {
                "id": "100076801902276",
                "count": 0
            },
            {
                "id": "61554505697690",
                "count": 0
            },
            {
                "id": "100000574813002",
                "count": 0
            },
            {
                "id": "61552595601359",
                "count": 0
            },
            {
                "id": "100036071297552",
                "count": 0
            },
            {
                "id": "100072659419001",
                "count": 0
            },
            {
                "id": "100040558276592",
                "count": 0
            },
            {
                "id": "100030661180098",
                "count": 0
            },
            {
                "id": "100078923513348",
                "count": 0
            },
            {
                "id": "100041885615110",
                "count": 0
            },
            {
                "id": "61550877991661",
                "count": 0
            },
            {
                "id": "100034645192868",
                "count": 0
            },
            {
                "id": "100084260606796",
                "count": 0
            },
            {
                "id": "100037604047018",
                "count": 0
            },
            {
                "id": "100087208038222",
                "count": 0
            },
            {
                "id": "100044497115675",
                "count": 0
            },
            {
                "id": "100023337000977",
                "count": 0
            },
            {
                "id": "100072860617426",
                "count": 0
            },
            {
                "id": "100014359039134",
                "count": 0
            },
            {
                "id": "100009793391816",
                "count": 0
            },
            {
                "id": "61564142953855",
                "count": 0
            },
            {
                "id": "100063787487497",
                "count": 0
            },
            {
                "id": "100080149855973",
                "count": 0
            },
            {
                "id": "100093325924420",
                "count": 0
            },
            {
                "id": "100038988972012",
                "count": 0
            },
            {
                "id": "100075513960894",
                "count": 0
            },
            {
                "id": "100038398534000",
                "count": 0
            },
            {
                "id": "61564170421535",
                "count": 0
            },
            {
                "id": "100078032562902",
                "count": 0
            },
            {
                "id": "61562187969494",
                "count": 0
            },
            {
                "id": "100093026747618",
                "count": 0
            },
            {
                "id": "100083942956835",
                "count": 0
            },
            {
                "id": "61554009424917",
                "count": 0
            },
            {
                "id": "61555847747044",
                "count": 0
            },
            {
                "id": "100086112716372",
                "count": 0
            },
            {
                "id": "100077289021351",
                "count": 0
            },
            {
                "id": "100087926503920",
                "count": 0
            },
            {
                "id": "100035628160194",
                "count": 0
            },
            {
                "id": "100050811503608",
                "count": 0
            },
            {
                "id": "100020528575783",
                "count": 0
            },
            {
                "id": "100095199310624",
                "count": 0
            },
            {
                "id": "100083304116208",
                "count": 0
            },
            {
                "id": "61554712072326",
                "count": 0
            },
            {
                "id": "100032049042314",
                "count": 0
            },
            {
                "id": "100093139814659",
                "count": 0
            },
            {
                "id": "100091325948910",
                "count": 0
            },
            {
                "id": "100092123136990",
                "count": 0
            },
            {
                "id": "100094102604190",
                "count": 0
            },
            {
                "id": "100077300294092",
                "count": 0
            },
            {
                "id": "100059101635841",
                "count": 0
            },
            {
                "id": "61556989617236",
                "count": 0
            },
            {
                "id": "100089269775183",
                "count": 0
            },
            {
                "id": "61554993582294",
                "count": 0
            },
            {
                "id": "100024133790484",
                "count": 0
            },
            {
                "id": "100092873784120",
                "count": 0
            },
            {
                "id": "100046292103991",
                "count": 0
            },
            {
                "id": "100028370918283",
                "count": 0
            },
            {
                "id": "100037865107893",
                "count": 0
            },
            {
                "id": "100070006783724",
                "count": 0
            },
            {
                "id": "100072236886559",
                "count": 0
            },
            {
                "id": "1578092979",
                "count": 0
            },
            {
                "id": "61553598653900",
                "count": 0
            },
            {
                "id": "100014679373226",
                "count": 0
            },
            {
                "id": "61568461416340",
                "count": 0
            },
            {
                "id": "100060796074174",
                "count": 0
            },
            {
                "id": "61566536774365",
                "count": 0
            },
            {
                "id": "100065563803743",
                "count": 0
            },
            {
                "id": "100080963384222",
                "count": 0
            },
            {
                "id": "100050590212254",
                "count": 0
            },
            {
                "id": "100020953182001",
                "count": 0
            },
            {
                "id": "100034985235308",
                "count": 0
            },
            {
                "id": "100073619405321",
                "count": 0
            },
            {
                "id": "100073677096216",
                "count": 0
            },
            {
                "id": "100095397240263",
                "count": 0
            },
            {
                "id": "100090989239372",
                "count": 0
            },
            {
                "id": "61556386283339",
                "count": 0
            },
            {
                "id": "100051223639760",
                "count": 0
            },
            {
                "id": "100088520275551",
                "count": 0
            },
            {
                "id": "100086552163685",
                "count": 0
            },
            {
                "id": "100050284906760",
                "count": 0
            },
            {
                "id": "100088684481575",
                "count": 0
            },
            {
                "id": "100075683283542",
                "count": 0
            },
            {
                "id": "100088285105412",
                "count": 0
            },
            {
                "id": "100084739688576",
                "count": 0
            },
            {
                "id": "100082452546345",
                "count": 0
            },
            {
                "id": "61559416928399",
                "count": 0
            },
            {
                "id": "61555349038001",
                "count": 0
            },
            {
                "id": "100090867101623",
                "count": 0
            },
            {
                "id": "100088947663299",
                "count": 0
            },
            {
                "id": "100043325152729",
                "count": 0
            },
            {
                "id": "100084479298103",
                "count": 0
            },
            {
                "id": "100046988973706",
                "count": 0
            },
            {
                "id": "61567265897789",
                "count": 0
            }
        ]
    }
}